{
  "locked": false,
  "version": 1,
  "targets": {
    "DNX,Version=v4.5.1": {
      "Microsoft.Azure.DocumentDB/1.4.1": {
        "dependencies": {
          "Newtonsoft.Json": "5.0.7"
        },
        "compile": {
          "lib/net40/Microsoft.Azure.Documents.Client.dll": {}
        },
        "runtime": {
          "lib/net40/Microsoft.Azure.Documents.Client.dll": {}
        }
      },
      "Microsoft.CSharp/4.0.0-beta-23109": {
        "frameworkAssemblies": [
          "Microsoft.CSharp"
        ],
        "compile": {
          "ref/net45/_._": {}
        },
        "runtime": {
          "lib/net45/_._": {}
        }
      },
      "Newtonsoft.Json/5.0.7": {
        "compile": {
          "lib/net45/Newtonsoft.Json.dll": {}
        },
        "runtime": {
          "lib/net45/Newtonsoft.Json.dll": {}
        }
      },
      "System.Collections/4.0.10-beta-23109": {
        "dependencies": {
          "System.Runtime": "4.0.0-beta-23109"
        },
        "compile": {
          "ref/dotnet/System.Collections.dll": {}
        }
      },
      "System.Linq/4.0.0-beta-23109": {
        "compile": {
          "ref/net45/_._": {}
        },
        "runtime": {
          "lib/net45/_._": {}
        }
      },
      "System.Runtime/4.0.10-beta-23109": {
        "compile": {
          "ref/net451/_._": {}
        },
        "runtime": {
          "lib/net451/_._": {}
        }
      },
      "System.Threading/4.0.10-beta-23109": {
        "dependencies": {
          "System.Runtime": "4.0.0-beta-23109",
          "System.Threading.Tasks": "4.0.0-beta-23109"
        },
        "compile": {
          "ref/dotnet/System.Threading.dll": {}
        }
      },
      "System.Threading.Tasks/4.0.0-beta-23109": {
        "compile": {
          "ref/net45/_._": {}
        },
        "runtime": {
          "lib/net45/_._": {}
        }
      }
    }
  },
  "libraries": {
    "Microsoft.Azure.DocumentDB/1.4.1": {
      "sha512": "7R6+JzygBYfjAClxcWZ/M3yO6TOCYTSaZGHX9jU6BikPADn7VpueNuebtf84hVhJxA562Hin3EvIjEJSKfulTA==",
      "files": [
        "lib/net40/Microsoft.Azure.Documents.Client.dll",
        "lib/net40/Microsoft.Azure.Documents.Client.XML",
        "Microsoft.Azure.DocumentDB.1.4.1.nupkg",
        "Microsoft.Azure.DocumentDB.1.4.1.nupkg.sha512",
        "Microsoft.Azure.DocumentDB.nuspec"
      ]
    },
    "Microsoft.CSharp/4.0.0-beta-23109": {
      "serviceable": true,
      "sha512": "MO4Lu8aMS1vL4Omp/gIMl2hr4sdV1l99p6xhAExGnS3MlFEa5JYPDL5mpdeg/osDH+1gAhb11xMJTYP7Ya3cAA==",
      "files": [
        "lib/dotnet/Microsoft.CSharp.dll",
        "lib/net45/_._",
        "lib/netcore50/Microsoft.CSharp.dll",
        "lib/win8/_._",
        "lib/wp80/_._",
        "lib/wpa81/_._",
        "Microsoft.CSharp.4.0.0-beta-23109.nupkg",
        "Microsoft.CSharp.4.0.0-beta-23109.nupkg.sha512",
        "Microsoft.CSharp.nuspec",
        "ref/dotnet/de/Microsoft.CSharp.xml",
        "ref/dotnet/es/Microsoft.CSharp.xml",
        "ref/dotnet/fr/Microsoft.CSharp.xml",
        "ref/dotnet/it/Microsoft.CSharp.xml",
        "ref/dotnet/ja/Microsoft.CSharp.xml",
        "ref/dotnet/ko/Microsoft.CSharp.xml",
        "ref/dotnet/Microsoft.CSharp.dll",
        "ref/dotnet/Microsoft.CSharp.xml",
        "ref/dotnet/ru/Microsoft.CSharp.xml",
        "ref/dotnet/zh-hans/Microsoft.CSharp.xml",
        "ref/dotnet/zh-hant/Microsoft.CSharp.xml",
        "ref/net45/_._",
        "ref/netcore50/Microsoft.CSharp.dll",
        "ref/netcore50/Microsoft.CSharp.xml",
        "ref/win8/_._",
        "ref/wp80/_._",
        "ref/wpa81/_._"
      ]
    },
    "Newtonsoft.Json/5.0.7": {
      "sha512": "vAtFRMm+LevObSOyI7wVlcS/b5LK7LxqMjKMUr5iDdvlxJbkWIR2+lN6h67MljPV4ZhaDHhepCbzy8BnqRJUhw==",
      "files": [
        "lib/net20/Newtonsoft.Json.dll",
        "lib/net20/Newtonsoft.Json.xml",
        "lib/net35/Newtonsoft.Json.dll",
        "lib/net35/Newtonsoft.Json.xml",
        "lib/net40/Newtonsoft.Json.dll",
        "lib/net40/Newtonsoft.Json.xml",
        "lib/net45/Newtonsoft.Json.dll",
        "lib/net45/Newtonsoft.Json.xml",
        "lib/netcore45/Newtonsoft.Json.dll",
        "lib/netcore45/Newtonsoft.Json.xml",
        "lib/portable-net40+sl4+wp7+win8/Newtonsoft.Json.dll",
        "lib/portable-net40+sl4+wp7+win8/Newtonsoft.Json.xml",
        "lib/portable-net45+wp80+win8/Newtonsoft.Json.dll",
        "lib/portable-net45+wp80+win8/Newtonsoft.Json.xml",
        "Newtonsoft.Json.5.0.7.nupkg",
        "Newtonsoft.Json.5.0.7.nupkg.sha512",
        "Newtonsoft.Json.nuspec",
        "tools/install.ps1"
      ]
    },
    "System.Collections/4.0.10-beta-23109": {
      "serviceable": true,
      "sha512": "2/VX+2QEyyIpvGDzuIXX8V0vSl/Llt673DR48nNmeA6BoMuwL4Eu4F1Meh9fPp80nhcjifqVK8g7/UQDn/0PFw==",
      "files": [
        "lib/DNXCore50/System.Collections.dll",
        "lib/net46/_._",
        "lib/netcore50/System.Collections.dll",
        "ref/dotnet/de/System.Collections.xml",
        "ref/dotnet/es/System.Collections.xml",
        "ref/dotnet/fr/System.Collections.xml",
        "ref/dotnet/it/System.Collections.xml",
        "ref/dotnet/ja/System.Collections.xml",
        "ref/dotnet/ko/System.Collections.xml",
        "ref/dotnet/ru/System.Collections.xml",
        "ref/dotnet/System.Collections.dll",
        "ref/dotnet/System.Collections.xml",
        "ref/dotnet/zh-hans/System.Collections.xml",
        "ref/dotnet/zh-hant/System.Collections.xml",
        "ref/net46/_._",
        "runtimes/win8-aot/lib/netcore50/System.Collections.dll",
        "System.Collections.4.0.10-beta-23109.nupkg",
        "System.Collections.4.0.10-beta-23109.nupkg.sha512",
        "System.Collections.nuspec"
      ]
    },
    "System.Linq/4.0.0-beta-23109": {
      "serviceable": true,
      "sha512": "NN0sQlEAjYDdMW5SU8p75niORiKwME2hRac30HB1QVUSuMtDs/easUBMJKGnXRHmxcrdwvHApfJOiH1tZ6eTbQ==",
      "files": [
        "lib/dotnet/System.Linq.dll",
        "lib/net45/_._",
        "lib/netcore50/System.Linq.dll",
        "lib/win8/_._",
        "lib/wp80/_._",
        "lib/wpa81/_._",
        "ref/dotnet/de/System.Linq.xml",
        "ref/dotnet/es/System.Linq.xml",
        "ref/dotnet/fr/System.Linq.xml",
        "ref/dotnet/it/System.Linq.xml",
        "ref/dotnet/ja/System.Linq.xml",
        "ref/dotnet/ko/System.Linq.xml",
        "ref/dotnet/ru/System.Linq.xml",
        "ref/dotnet/System.Linq.dll",
        "ref/dotnet/System.Linq.xml",
        "ref/dotnet/zh-hans/System.Linq.xml",
        "ref/dotnet/zh-hant/System.Linq.xml",
        "ref/net45/_._",
        "ref/netcore50/System.Linq.dll",
        "ref/netcore50/System.Linq.xml",
        "ref/win8/_._",
        "ref/wp80/_._",
        "ref/wpa81/_._",
        "System.Linq.4.0.0-beta-23109.nupkg",
        "System.Linq.4.0.0-beta-23109.nupkg.sha512",
        "System.Linq.nuspec"
      ]
    },
    "System.Runtime/4.0.10-beta-23109": {
      "sha512": "dWIEUlq0pMQWq803mv2eF6TfN5zxGNW0OuFLwDEqDTwBvNlAmUbWgh7g6zBL5xyNiMC6wPUoL35tZOpPHIiHyw==",
      "files": [
        "lib/net451/_._",
        "lib/win81/_._",
        "lib/wpa81/_._",
        "License.rtf",
        "ref/dotnet/de/System.Runtime.xml",
        "ref/dotnet/es/System.Runtime.xml",
        "ref/dotnet/fr/System.Runtime.xml",
        "ref/dotnet/it/System.Runtime.xml",
        "ref/dotnet/ja/System.Runtime.xml",
        "ref/dotnet/ko/System.Runtime.xml",
        "ref/dotnet/ru/System.Runtime.xml",
        "ref/dotnet/System.Runtime.dll",
        "ref/dotnet/System.Runtime.xml",
        "ref/dotnet/zh-hans/System.Runtime.xml",
        "ref/dotnet/zh-hant/System.Runtime.xml",
        "ref/net451/_._",
        "ref/netcore50/de/System.Runtime.xml",
        "ref/netcore50/es/System.Runtime.xml",
        "ref/netcore50/fr/System.Runtime.xml",
        "ref/netcore50/it/System.Runtime.xml",
        "ref/netcore50/ja/System.Runtime.xml",
        "ref/netcore50/ko/System.Runtime.xml",
        "ref/netcore50/ru/System.Runtime.xml",
        "ref/netcore50/System.Runtime.dll",
        "ref/netcore50/System.Runtime.xml",
        "ref/netcore50/zh-hans/System.Runtime.xml",
        "ref/netcore50/zh-hant/System.Runtime.xml",
        "ref/win81/_._",
        "ref/wpa81/_._",
        "System.Runtime.4.0.10-beta-23109.nupkg",
        "System.Runtime.4.0.10-beta-23109.nupkg.sha512",
        "System.Runtime.nuspec"
      ]
    },
    "System.Threading/4.0.10-beta-23109": {
      "serviceable": true,
      "sha512": "TSViw+K20yh9DmwzZpvuCUc2m2ju1eVAJ10pTw2gB/aP4kkrX2nGf4A9BkwkxupPXFA2OtO9LbbEqdp4YbBnjQ==",
      "files": [
        "lib/DNXCore50/System.Threading.dll",
        "lib/net46/_._",
        "lib/netcore50/System.Threading.dll",
        "ref/dotnet/de/System.Threading.xml",
        "ref/dotnet/es/System.Threading.xml",
        "ref/dotnet/fr/System.Threading.xml",
        "ref/dotnet/it/System.Threading.xml",
        "ref/dotnet/ja/System.Threading.xml",
        "ref/dotnet/ko/System.Threading.xml",
        "ref/dotnet/ru/System.Threading.xml",
        "ref/dotnet/System.Threading.dll",
        "ref/dotnet/System.Threading.xml",
        "ref/dotnet/zh-hans/System.Threading.xml",
        "ref/dotnet/zh-hant/System.Threading.xml",
        "ref/net46/_._",
        "runtimes/win8-aot/lib/netcore50/System.Threading.dll",
        "System.Threading.4.0.10-beta-23109.nupkg",
        "System.Threading.4.0.10-beta-23109.nupkg.sha512",
        "System.Threading.nuspec"
      ]
    },
    "System.Threading.Tasks/4.0.0-beta-23109": {
      "sha512": "RLZMGWis+RKdXShPOswRacJujHuyiCKw71uw8diEvyHMGa8GT7Gmv6g7U5t8DYZ2V8VMMYbbJaAEmT4tSd4REA==",
      "files": [
        "lib/net45/_._",
        "lib/win8/_._",
        "lib/wp80/_._",
        "lib/wpa81/_._",
        "License.rtf",
        "ref/dotnet/de/System.Threading.Tasks.xml",
        "ref/dotnet/es/System.Threading.Tasks.xml",
        "ref/dotnet/fr/System.Threading.Tasks.xml",
        "ref/dotnet/it/System.Threading.Tasks.xml",
        "ref/dotnet/ja/System.Threading.Tasks.xml",
        "ref/dotnet/ko/System.Threading.Tasks.xml",
        "ref/dotnet/ru/System.Threading.Tasks.xml",
        "ref/dotnet/System.Threading.Tasks.dll",
        "ref/dotnet/System.Threading.Tasks.xml",
        "ref/dotnet/zh-hans/System.Threading.Tasks.xml",
        "ref/dotnet/zh-hant/System.Threading.Tasks.xml",
        "ref/net45/_._",
        "ref/netcore50/de/System.Threading.Tasks.xml",
        "ref/netcore50/es/System.Threading.Tasks.xml",
        "ref/netcore50/fr/System.Threading.Tasks.xml",
        "ref/netcore50/it/System.Threading.Tasks.xml",
        "ref/netcore50/ja/System.Threading.Tasks.xml",
        "ref/netcore50/ko/System.Threading.Tasks.xml",
        "ref/netcore50/ru/System.Threading.Tasks.xml",
        "ref/netcore50/System.Threading.Tasks.dll",
        "ref/netcore50/System.Threading.Tasks.xml",
        "ref/netcore50/zh-hans/System.Threading.Tasks.xml",
        "ref/netcore50/zh-hant/System.Threading.Tasks.xml",
        "ref/win8/_._",
        "ref/wp80/_._",
        "ref/wpa81/_._",
        "System.Threading.Tasks.4.0.0-beta-23109.nupkg",
        "System.Threading.Tasks.4.0.0-beta-23109.nupkg.sha512",
        "System.Threading.Tasks.nuspec"
      ]
    }
  },
  "projectFileDependencyGroups": {
    "": [
      "System.Collections >= 4.0.10-beta-23109",
      "System.Linq >= 4.0.0-beta-23109",
      "System.Threading >= 4.0.10-beta-23109",
      "System.Runtime >= 4.0.10-beta-23109",
      "Microsoft.CSharp >= 4.0.0-beta-23109",
      "Microsoft.Azure.DocumentDB >= 1.4.1"
    ],
    "DNX,Version=v4.5.1": [
      "Microsoft.Azure.DocumentDB >= 1.4.1"
    ]
  }
}